{
  "project_info": {
    "project_number": "76605639865",
    "firebase_url": "https://as-fashion-cf556-default-rtdb.firebaseio.com",
    "project_id": "as-fashion-cf556",
    "storage_bucket": "as-fashion-cf556.appspot.com"
  },
  "client": [
    {
      "client_info": {
        "mobilesdk_app_id": "1:76605639865:android:2cccc4c3e124634e931f68",
        "android_client_info": {
          "package_name": "com.yadavtechnical.adminpanel"
        }
      },
      "oauth_client": [
        {
          "client_id": "76605639865-96u74u7ehcu1kecra3b5v6vc9gfpuvsh.apps.googleusercontent.com",
          "client_type": 3
        }
      ],
      "api_key": [
        {
          "current_key": "AIzaSyDgaLs9D9zpFp67b8EHEkYBWUVdaZB2bFM"
        }
      ],
      "services": {
        "appinvite_service": {
          "other_platform_oauth_client": [
            {
              "client_id": "76605639865-96u74u7ehcu1kecra3b5v6vc9gfpuvsh.apps.googleusercontent.com",
              "client_type": 3
            }
          ]
        }
      }
    },
    {
      "client_info": {
        "mobilesdk_app_id": "1:76605639865:android:d787504985a769b2931f68",
        "android_client_info": {
          "package_name": "com.yadavtechnicalcorp.asfashion"
        }
      },
      "oauth_client": [
        {
          "client_id": "76605639865-96u74u7ehcu1kecra3b5v6vc9gfpuvsh.apps.googleusercontent.com",
          "client_type": 3
        }
      ],
      "api_key": [
        {
          "current_key": "AIzaSyDgaLs9D9zpFp67b8EHEkYBWUVdaZB2bFM"
        }
      ],
      "services": {
        "appinvite_service": {
          "other_platform_oauth_client": [
            {
              "client_id": "76605639865-96u74u7ehcu1kecra3b5v6vc9gfpuvsh.apps.googleusercontent.com",
              "client_type": 3
            }
          ]
        }
      }
    }
  ],
  "configuration_version": "1"
}